{"bilisharp_api_bilivideo.md":"323b4b98","bilisharp_guide_first-video.md":"4c4fb4be","bilisharp_guide_get-credential.md":"714db97b","bilisharp_index.md":"86ab8bbe","yukichan_arcaea.md":"3f2c816b","yukichan_gallery.md":"ff4ce00a","yukichan_index.md":"c01d1602","yukichan_intro.md":"e773e3d6","yukichan_misc.md":"2d79f0f3","yukichan_trans.md":"c0a08b9a","yukichan_v1_arcaea.md":"af0db65c","yukichan_v1_bilibili.md":"9120dd15","yukichan_v1_code.md":"4d17f5fa","yukichan_v1_index.md":"342eda4f","yukichan_v1_trans.md":"e67a540a","yukichan_v1_wolframalpha.md":"d9f46dcd","yukichan_wolframalpha.md":"7338b50d","index.md":"569b07b9","lancelot_arcaea.md":"9d67324b","lancelot_changelog.md":"47708c94","lancelot_index.md":"645ddcb0","lancelot_poke.md":"3fc2cd49","lancelot_tools.md":"2ed05236","lancelot_utils.md":"133cfe4a"}
